communicate_with_TFS_lib/__init__.py
communicate_with_TFS_lib/communicate_TFS.py
communicate_with_TFS_lib/create_config_file.py
communicate_with_TFS_lib/featch_testcases_from_TFS.py
get_test_cases_from_TFS-0.3.0.dist-info/METADATA
get_test_cases_from_TFS-0.3.0.dist-info/WHEEL
get_test_cases_from_TFS-0.3.0.dist-info/top_level.txt
get_test_cases_from_TFS-0.3.0.dist-info/RECORD
