Metadata-Version: 2.1
Name: get-test-cases-from-TFS
Version: 0.3.0
Summary: this Lib is to get the TFS testPlan data, and communicate with TFS API to get the test cases from TFS. Then extract the Testcases as XML file.
Author: Ayman Mansour, Mohanad Hesham
Author-email: Ayman.Mansour@integrant.com, Mohanad.hesham@integrant.com
Classifier: Programming Language :: Python :: 3
Classifier: License :: OSI Approved :: MIT License
Classifier: Operating System :: OS Independent
Requires-Python: >=3.6
Requires-Dist: aiohttp ==3.9.3
Requires-Dist: aiosignal ==1.3.1
Requires-Dist: annotated-types ==0.6.0
Requires-Dist: anyio ==4.3.0
Requires-Dist: asttokens ==2.4.1
Requires-Dist: attrs ==23.2.0
Requires-Dist: backcall ==0.2.0
Requires-Dist: backports.tarfile ==1.2.0
Requires-Dist: bleach ==6.1.0
Requires-Dist: certifi ==2024.2.2
Requires-Dist: charset-normalizer ==3.3.2
Requires-Dist: click ==8.1.7
Requires-Dist: colorama ==0.4.6
Requires-Dist: dataclasses-json ==0.6.4
Requires-Dist: decorator ==5.1.1
Requires-Dist: defusedxml ==0.7.1
Requires-Dist: distro ==1.9.0
Requires-Dist: dnspython ==2.6.1
Requires-Dist: docopt ==0.6.2
Requires-Dist: docutils ==0.21.2
Requires-Dist: email-validator ==2.1.0.post1
Requires-Dist: et-xmlfile ==1.1.0
Requires-Dist: executing ==2.0.1
Requires-Dist: fastapi ==0.109.2
Requires-Dist: fastjsonschema ==2.20.0
Requires-Dist: frozenlist ==1.4.1
Requires-Dist: greenlet ==3.0.3
Requires-Dist: h11 ==0.14.0
Requires-Dist: httpcore ==1.0.3
Requires-Dist: httptools ==0.6.1
Requires-Dist: httpx ==0.26.0
Requires-Dist: idna ==3.6
Requires-Dist: importlib-metadata ==7.2.1
Requires-Dist: iniconfig ==2.0.0
Requires-Dist: itsdangerous ==2.1.2
Requires-Dist: jaraco.classes ==3.4.0
Requires-Dist: jaraco.context ==5.3.0
Requires-Dist: jaraco.functools ==4.0.1
Requires-Dist: Jinja2 ==3.1.3
Requires-Dist: jsonpatch ==1.33
Requires-Dist: jsonpointer ==2.4
Requires-Dist: jupyter-core ==5.7.2
Requires-Dist: jupyterlab-pygments ==0.3.0
Requires-Dist: keyring ==25.2.1
Requires-Dist: langchain ==0.1.8
Requires-Dist: langchain-community ==0.0.21
Requires-Dist: langchain-core ==0.1.24
Requires-Dist: langchain-openai ==0.0.6
Requires-Dist: langsmith ==0.1.3
Requires-Dist: markdown-it-py ==3.0.0
Requires-Dist: MarkupSafe ==2.1.5
Requires-Dist: marshmallow ==3.20.2
Requires-Dist: matplotlib-inline ==0.1.7
Requires-Dist: mdurl ==0.1.2
Requires-Dist: mistune ==3.0.2
Requires-Dist: more-itertools ==10.3.0
Requires-Dist: multidict ==6.0.5
Requires-Dist: mypy-extensions ==1.0.0
Requires-Dist: nh3 ==0.2.17
Requires-Dist: numpy ==1.26.4
Requires-Dist: openai ==1.12.0
Requires-Dist: openpyxl ==3.1.2
Requires-Dist: orjson ==3.9.14
Requires-Dist: packaging ==23.2
Requires-Dist: pandas ==2.2.0
Requires-Dist: pandocfilters ==1.5.1
Requires-Dist: parso ==0.8.4
Requires-Dist: pickleshare ==0.7.5
Requires-Dist: pkginfo ==1.11.1
Requires-Dist: platformdirs ==4.2.2
Requires-Dist: pluggy ==1.4.0
Requires-Dist: prompt-toolkit ==3.0.47
Requires-Dist: pure-eval ==0.2.2
Requires-Dist: pyarrow ==15.0.0
Requires-Dist: pydantic ==2.6.1
Requires-Dist: pydantic-extra-types ==2.5.0
Requires-Dist: pydantic-settings ==2.2.1
Requires-Dist: pydantic-core ==2.16.2
Requires-Dist: Pygments ==2.18.0
Requires-Dist: pyparsing ==3.1.2
Requires-Dist: pytest ==8.1.1
Requires-Dist: python-dateutil ==2.8.2
Requires-Dist: python-dotenv ==1.0.1
Requires-Dist: python-multipart ==0.0.9
Requires-Dist: pytz ==2024.1
Requires-Dist: pywin32 ==306
Requires-Dist: pywin32-ctypes ==0.2.2
Requires-Dist: PyYAML ==6.0.1
Requires-Dist: pyzmq ==26.0.3
Requires-Dist: readme-renderer ==43.0
Requires-Dist: referencing ==0.35.1
Requires-Dist: regex ==2023.12.25
Requires-Dist: requests ==2.31.0
Requires-Dist: requests-toolbelt ==1.0.0
Requires-Dist: rfc3986 ==2.0.0
Requires-Dist: rich ==13.7.1
Requires-Dist: rpds-py ==0.18.1
Requires-Dist: six ==1.16.0
Requires-Dist: sniffio ==1.3.0
Requires-Dist: soupsieve ==2.5
Requires-Dist: SQLAlchemy ==2.0.27
Requires-Dist: stack-data ==0.6.3
Requires-Dist: starlette ==0.36.3
Requires-Dist: tenacity ==8.2.3
Requires-Dist: tiktoken ==0.6.0
Requires-Dist: tinycss2 ==1.3.0
Requires-Dist: tornado ==6.4.1
Requires-Dist: tqdm ==4.66.2
Requires-Dist: traitlets ==5.14.3
Requires-Dist: twine ==5.1.0
Requires-Dist: typing-inspect ==0.9.0
Requires-Dist: typing-extensions ==4.9.0
Requires-Dist: tzdata ==2024.1
Requires-Dist: ujson ==5.9.0
Requires-Dist: urllib3 ==2.2.1
Requires-Dist: uvicorn ==0.27.1
Requires-Dist: watchfiles ==0.21.0
Requires-Dist: wcwidth ==0.2.13
Requires-Dist: webencodings ==0.5.1
Requires-Dist: websockets ==12.0
Requires-Dist: xmltodict ==0.13.0
Requires-Dist: yarg ==0.1.9
Requires-Dist: yarl ==1.9.4
Requires-Dist: zipp ==3.19.2
